.gitignore
CHANGES.txt
LICENSE.txt
MANIFEST.in
README.rst
setup.py
pyiface/__init__.py
pyiface/iface.py
pyiface/ifreqioctls.py
pyiface.egg-info/PKG-INFO
pyiface.egg-info/SOURCES.txt
pyiface.egg-info/dependency_links.txt
pyiface.egg-info/top_level.txt