Metadata-Version: 1.2
Name: pyiface
Version: 0.1.dev33
Summary: View and control network interfaces. Linux only currently! Join us lets make it available for other OSes
Home-page: http://pypi.python.org/pypi/pyiface/
Author: Sergey Kostov
Author-email: bat.serjo@gmail.com
License: LICENSE.txt
Platform: UNKNOWN
Requires-Python: >=2
